{
  "title" : "micro:bit",
  "publisherName" : "Micro:bit Educational Foundation",
  "feedIdentifier" : "org.microbit.swift-playgrounds",
  "contactURL" : "http://microbit.org/testing#swiftplaygrounds",
  "formatVersion" : "1.0",
  "documents" : [
    {
      "title" : "Intro to the BBC micro꞉bit",
      "overviewSubtitle" : "An introduction to the BBC micro:bit.",
      "detailSubtitle" : "Learn how to control the micro:bit using Swift.",
      "description" : "",
      "difficultyLevel" : "intermediate",
      "contentIdentifier" : "org.microbit.swift-playgrounds.microbit-intro",
      "contentVersion" : "1.1.0",
      "url" : "https://microbit.org/swift-playgrounds/intro.playgroundbook.zip",
      "publishedDate" : "2018-09-26T13:30:00+01:00",
      "lastUpdatedDate" : "2018-11-17T13:30:00+01:00",
      "thumbnailURL" : "intro_thumbnail.png",
      "bannerImageURL" : "intro_banner.png",
      "additionalInformation" : [
        {
          "name" : "Languages",
          "value" : "English"
        }
      ],
      "previewImageURLs" : [
        "preview-1.png",
        "preview-2.png",
        "preview-3.png"
      ]
    }
  ]
}